orangypy/__init__.py
orangypy/animation.py
orangypy/audio.py
orangypy/colors.py
orangypy/core.py
orangypy/input.py
orangypy/shapes.py
orangypy/sprite.py
orangypy-0.1.0.dist-info/METADATA
orangypy-0.1.0.dist-info/WHEEL
orangypy-0.1.0.dist-info/top_level.txt
orangypy-0.1.0.dist-info/RECORD
