Metadata-Version: 2.4
Name: orangypy
Version: 0.1.0
Summary: Motor de juegos ultra simple basado en Pygame es como un plugin para facilitar
Author-email: Orangy_Dev <bustillodanelia15@gmail.com>
Requires-Python: >=3.10
Requires-Dist: pygame>=2.5
